compose_to_render/__init__.py
compose_to_render/main.py
compose_to_render/models.py
compose_to_render/translator.py
compose_to_render-0.1.0.dist-info/LICENSE
compose_to_render-0.1.0.dist-info/METADATA
compose_to_render-0.1.0.dist-info/WHEEL
compose_to_render-0.1.0.dist-info/entry_points.txt
compose_to_render-0.1.0.dist-info/RECORD
